studies/__init__.py
studies/admin.py
studies/apps.py
studies/experiments.py
studies/models.py
studies/validators.py
studies/migrations/0001_initial.py
studies/migrations/__init__.py
django_studies-0.1.2.dist-info/LICENSE
django_studies-0.1.2.dist-info/METADATA
django_studies-0.1.2.dist-info/WHEEL
django_studies-0.1.2.dist-info/top_level.txt
django_studies-0.1.2.dist-info/RECORD
