Metadata-Version: 2.1
Name: django-studies
Version: 0.1.2
Summary: Run experiments in you Django project
Home-page: https://github.com/fitodic/django-studies
Author: Filip Todić
Author-email: todic.filip@gmail.com
License: MIT
Keywords: Django,experiments
Platform: POSIX
Platform: Microsoft
Platform: MacOS
Classifier: Development Status :: 4 - Beta
Classifier: Environment :: Web Environment
Classifier: Environment :: Plugins
Classifier: Framework :: Django
Classifier: Framework :: Django :: 3.2
Classifier: Framework :: Django :: 4.0
Classifier: Intended Audience :: Developers
Classifier: License :: OSI Approved :: MIT License
Classifier: Operating System :: OS Independent
Classifier: Programming Language :: Python
Classifier: Programming Language :: Python :: 3.8
Classifier: Programming Language :: Python :: 3.9
Classifier: Programming Language :: Python :: 3.10
Classifier: Topic :: Internet
Classifier: Topic :: Internet :: WWW/HTTP
Classifier: Topic :: Internet :: WWW/HTTP :: HTTP Servers
Classifier: Topic :: Software Development
Classifier: Topic :: Software Development :: Bug Tracking
Classifier: Topic :: Software Development :: Libraries :: Python Modules
Classifier: Topic :: Software Development :: Testing
Classifier: Topic :: Software Development :: Testing :: Acceptance
Classifier: Topic :: System :: Logging
Classifier: Topic :: System :: Networking :: Monitoring
Classifier: Topic :: Utilities
Requires-Python: >=3.8
License-File: LICENSE
Requires-Dist: Django (>=3.2)
Requires-Dist: laboratory (>=1.0)
Provides-Extra: dev
Requires-Dist: tox ; extra == 'dev'
Requires-Dist: ipdb ; extra == 'dev'
Requires-Dist: django-configurations[database] ; extra == 'dev'
Provides-Extra: lint
Requires-Dist: isort ; extra == 'lint'
Requires-Dist: black ; extra == 'lint'
Requires-Dist: flake8 ; extra == 'lint'
Provides-Extra: test
Requires-Dist: ipdb ; extra == 'test'
Requires-Dist: coverage ; extra == 'test'
Requires-Dist: pytest (>=3.0) ; extra == 'test'
Requires-Dist: pytest-django ; extra == 'test'
Requires-Dist: pytest-runner ; extra == 'test'
Requires-Dist: django-configurations[database] ; extra == 'test'
